same_stats/__init__.py
same_stats/__main__.py
same_stats/same_stats.py
same_stats/seed_datasets/Datasaurus_data.csv
same_stats/seed_datasets/angled_blob.csv
same_stats/seed_datasets/less_angled_blob.csv
same_stats/seed_datasets/random_cloud.csv
same_stats/seed_datasets/slanted_less.csv
same_stats-0.1.1.dist-info/WHEEL
same_stats-0.1.1.dist-info/METADATA
same_stats-0.1.1.dist-info/RECORD
