Metadata-Version: 2.1
Name: same-stats
Version: 0.1.1
Summary: A tool to create datasets with different graphs but the same statistics
Home-page: https://github.com/khuyentran1401/same-stats-different-graphs
License: Apache-2.0
Keywords: statistics,graphs,data visualization
Author: khuyentran1401
Author-email: khuyentran1476@gmail.com
Requires-Python: >=3.7,<4.0
Classifier: License :: OSI Approved :: Apache Software License
Classifier: Programming Language :: Python :: 3
Classifier: Programming Language :: Python :: 3.7
Classifier: Programming Language :: Python :: 3.8
Classifier: Programming Language :: Python :: 3.9
Requires-Dist: PyTweening (==1.0.3)
Requires-Dist: matplotlib (>=3.4.2,<4.0.0)
Requires-Dist: seaborn (>=0.11.1,<0.12.0)
Requires-Dist: tqdm (>=4.61.1,<5.0.0)
Project-URL: Repository, https://github.com/khuyentran1401/same-stats-different-graphs
